{
  "f01277": "active, Sweden, Stockholm, tvsthlm",
  "f01278": "active, USA, Grand Rapids, MiMiner",
  "f01291": "active, Sweden, Stockholm, tvsthlm",
  "f01782": "active, China, Hong Kong + Singapore + USA, Portland, hellofil.com",
  "f02401": "active, Canada, Chambly, NBFS Canada",
  "f02415": "active, China, Hong Kong",
  "f02423": "active, Ukraine, Kyiv, igowreck",
  "f02490": "active, China, Fujian",
  "f02501": "active, USA, Portland, 6block",
  "f02514": "active, USA, Portland, 6block",
  "f02620": "active, Poland, Krakow, @magik6k",
  "f02622": "active, USA, Portland, 6block",
  "f02633": "active, China, Hong Kong",
  "f02645": "active, China, Hong Kong",
  "f03339": "active, China, Luzhou, benxun",
  "f05316": "active, USA, Portland, 6block",
  "f05664": "active, China, Shenzhen, 艾比特网络科技",
  "f07850": "active, USA, Portland, 6block",
  "f08025": "active, China, Hong Kong",
  "f08103": "active, China, Foshan, 花生酱肠粉",
  "f09693": "active, USA, Portland + Singapore",
  "f09848": "active, USA",
  "f010084": "active, China, Beijing",
  "f010247": "active, China, Yantai",
  "f010479": "active, France, Fontenay-sous-Bois",
  "f010491": "active, China, Shenzhen",
  "f010505": "active, China, Wuhan",
  "f010523": "active, China, Beijing",
  "f010617": "active, Canada, Surrey, @feiya200",
  "f014394": "active, China, Suzhou",
  "f014409": "active, USA, Waxhaw",
  "f015877": "active, China, Jiaxing + USA",
  "f015941": "active, Ukraine, Kyiv",
  "f018501": "active, China, Beijing",
  "f018781": "active, Singapore + Germany, Frankfurt + USA",
  "f019100": "active, Romania, Cluj-Napoca",
  "f019240": "active, China, Beijing",
  "f019551": "active, UK, Birmingham, @Neofix AF",
  "f020378": "active, Bulgaria, Asenovgrad",
  "f020489": "active, China, Lioaning",
  "f020523": "active, China, Suzhou",
  "f022125": "active, China, Shenzhen",
  "f022142": "active, USA, Queens",
  "f022308": "active, NR",
  "f022522": "active, China, Dongguan",
  "f022853": "active, China, Fuzhou",
  "f023467": "active, Norway, Oslo",
  "f023495": "active, China, Beijing + USA, Portland",
  "f023825": "active, USA, Portland",
  "f023843": "active, NR",
  "f024015": "active, USA, Portland",
  "f024016": "active, USA, Portland",
  "f024184": "active, Korea, Gangnam-gu",
  "f025007": "active, Korea, Gyeonggi-do",
  "f025017": "active, China, Hefei",
  "f029401": "active, USA, Portland + New Castle",
  "f029404": "active, USA, Portland + New Castle",
  "f029524": "active, China, Hong Kong",
  "f030379": "active, Korea, Uiwang",
  "f034701": "active, China, Shenzhen",
  "f038299": "active, Russia, St. Petersburg",
  "f042540": "active, China, Beijing + USA, Portland + Newcastle",
  "f042558": "active, China, Beijing + USA, Portland + Newcastle",
  "f042635": "active, China, Beijing + USA, Portland + Newcastle",
  "f044021": "active, China, Dongguan",
  "f044160": "active, China, Guangzhou",
  "f047858": "active, China, Wuhan",
  "f048135": "active, China, Chongqing",
  "f048172": "active, China, Suzhou",
  "f048192": "active, China, Suzhou",
  "f052447": "active, China, Beijing + USA, Portland + New Castle",
  "f053916": "active, USA, Concord",
  "f054163": "active, China, Dongguan",
  "f054370": "active, China, Dongguan",
  "f054389": "active, China, Chongqing",
  "f056611": "active, USA, Portland + New Castle",
  "f057368": "active, Korea, Gyeonggi-do",
  "f057560": "active, NR",
  "f057614": "active, USA, Portland + New Castle",
  "f057842": "active, Korea, Gyeonggi-do",
  "f058168": "active, Korea, Gyeonggi-do",
  "f060072": "active, China, Chongqing",
  "f061158": "active, China, Guangdong",
  "f062260": "active, China, Guangzhou",
  "f062318": "active, Korea, Naju",
  "f02576": "active-sealing, Denmark, Gjerlev, BenjaminH",
  "f03273": "active-sealing, USA, Portland, 6block",
  "f03274": "active-sealing, USA, Portland, 6block",
  "f010241": "active-sealing, China, Beijing + USA, Portland",
  "f010253": "active-sealing, China, Beijing + USA, Portland",
  "f019104": "active-sealing, Canada, Chambly",
  "f023971": "active-sealing, USA, @Brian Y",
  "f01241": "sealing, USA, Portland, 6block",
  "f01287": "sealing, China, Jiaxing, MaiTian",
  "f01799": "sealing, China, Jinan, TokenHome",
  "f03134": "sealing, China, Cangzhou, 乔木信息",
  "f03222": "sealing, China, Yuncheong, 星云矿池",
  "f03224": "sealing, Ukraine, Irpin, oboltusov",
  "f03328": "sealing, China, Xinxiang",
  "f03345": "sealing, China, Fuzhou, chh",
  "f03482": "sealing, China, Wuxi",
  "f03624": "sealing, Germany, Chemnitz, ode",
  "f05315": "sealing, USA, Portland, 6block",
  "f07990": "sealing, China, Hong Kong",
  "f08157": "sealing, China, Beijing + Germany, Frankfurt, 超星际",
  "f08383": "sealing, USA, Portland, 6block",
  "f08482": "sealing, USA, Athol, @why",
  "f09696": "sealing, USA, Portland + Singapore",
  "f010493": "sealing, China, Shanghai",
  "f010498": "sealing, China, Shenzhen",
  "f010501": "sealing, China, Hangzhou",
  "f010528": "sealing, China, Chongqing",
  "f015747": "sealing, Japan, Setagaya-ku",
  "f016594": "sealing, Germany",
  "f019824": "sealing, USA",
  "f020398": "sealing, China, Zhangjiakou",
  "f020904": "sealing, Korea, Uijeongbu-si",
  "f020928": "sealing, China, Deyang + Singapore",
  "f021339": "sealing, China, Jiaxing",
  "f021583": "sealing, China, Jiaxing",
  "f022089": "sealing, China, Beijing",
  "f022261": "sealing, China, Luzhou",
  "f022922": "sealing, China, Shenzhen",
  "f025044": "sealing, undefined",
  "f032934": "sealing, Korea, Incheon",
  "f034084": "sealing, China, Chongqing",
  "f035436": "sealing, China, Jiangsu",
  "f039515": "sealing, China, Chongqing",
  "f043929": "sealing, China, Beijing",
  "f045555": "sealing, China, Chongqing",
  "f047978": "sealing, Korea, Seoul",
  "f049772": "sealing, Korea, Seoul",
  "f050500": "sealing, Korea, Uiwang",
  "f053037": "sealing, China, Hefei",
  "f053088": "sealing, China, Shanghai",
  "f054677": "sealing, Finland, Helsinki",
  "f055040": "sealing, China, Fujian",
  "f055171": "sealing, China, Maoming",
  "f056443": "sealing, Korea, Gyeonggi-do",
  "f056573": "sealing, China, Sichuan",
  "f058000": "sealing, China, Suzhou",
  "f062204": "sealing, China, Hong Kong",
  "f062375": "sealing, Korea, Gyeonggi-do",
  "f02665": "stuck, Netherlands, Amsterdam, fm-ops",
  "f014768": "stuck, Singapore, @Funk",
  "f019534": "stuck, USA, Beaverton",
  "f022163": "stuck, NR",
  "f040173": "stuck, Ukraine, Ternopil",
  "f055123": "stuck, Korea, Busan",
  "f058374": "stuck, USA",
  "f062334": "stuck, USA, Portland + New Castle",
  "f062353": "stuck, Germany",
  "f01240": "min-size, Netherlands, HidNand",
  "f02299": "min-size, China, Dongguan, Yolo",
  "f09569": "min-size, China, Beijing",
  "f023868": "min-size, China, Fuzhou",
  "f023869": "min-size, China, Fuzhou",
  "f023870": "min-size, China, Fuzhou",
  "f023876": "min-size, China, Fuzhou",
  "f023978": "min-size, China, Fuzhou",
  "f024012": "min-size, China, Fuzhou",
  "f024013": "min-size, China, Fuzhou",
  "f024014": "min-size, China, Fuzhou",
  "f024136": "min-size, China, Fuzhou",
  "f01234": "min-ask, Belgium, De Klinge, Eliovp",
  "f01276": "min-ask, Canada, Brampton, NBFS Canada",
  "f01279": "min-ask, China, Sichuan",
  "f01289": "min-ask, China, Hangzhou + USA",
  "f02301": "min-ask, USA",
  "f02381": "min-ask, China, Dongguan, 西野七濑迷叔",
  "f02387": "min-ask, Canada, Brampton, NBFS Canada",
  "f02405": "min-ask, China, Shenzhen",
  "f02419": "min-ask, China, Shanghai, yuantai",
  "f02520": "min-ask, China, Hong Kong + Dongguan",
  "f02623": "min-ask, USA, Portland, 6block",
  "f03275": "min-ask, USA, Portland, 6block",
  "f03488": "min-ask, Korea, Geumcheon-gu",
  "f07919": "min-ask, China, Beijing, Shanghai, Hunan",
  "f08220": "min-ask, China, Shenzhen",
  "f08257": "min-ask, China, Ningbo + USA, Boardman",
  "f010254": "min-ask, Japan, Minamata",
  "f014365": "min-ask, Australia, Marrickville + Japan, Heiwajima",
  "f018780": "min-ask, Singapore + Germany, Frankfurt + USA",
  "f019029": "min-ask, Serbia, Boljevac",
  "f019362": "min-ask, China, Hangzhou",
  "f020223": "min-ask, China, Guiyang",
  "f020541": "min-ask, China, Shanghai",
  "f020747": "min-ask, China, Xiamen",
  "f021265": "min-ask, China, Wuhan",
  "f021540": "min-ask, Germany, Frankfurt, @hsanjuan",
  "f022352": "min-ask, Norway, Borgen",
  "f023001": "min-ask, China, Changsha",
  "f023565": "min-ask, China, Fuzhou",
  "f023660": "min-ask, China, Fuzhou",
  "f023853": "min-ask, China, Fuzhou",
  "f023854": "min-ask, China, Fuzhou",
  "f023855": "min-ask, China, Fuzhou",
  "f023861": "min-ask, China, Fuzhou",
  "f024006": "min-ask, China, Fuzhou",
  "f024007": "min-ask, China, Fuzhou",
  "f024008": "min-ask, China, Fuzhou",
  "f024081": "min-ask, undefined",
  "f024084": "min-ask, China, Fuzhou",
  "f024085": "min-ask, China, Fuzhou",
  "f024127": "min-ask, China, Fuzhou",
  "f033511": "min-ask, China, Dongguan",
  "f034047": "min-ask, China, Hangzhou",
  "f034581": "min-ask, NR",
  "f034592": "min-ask, NR",
  "f039873": "min-ask, China, Fuzhou",
  "f01238": "error, Vietnam, Hanoi, FILECOIN-VIETNAM",
  "f01280": "error, China, Wuxi, 了凡超算",
  "f02540": "error, USA, Rochester",
  "f02619": "error, China, Beijing, Blockcasting",
  "f02824": "error, China, Chengdu",
  "f03491": "error, China, Hong Kong",
  "f010400": "error, China, Shenyang",
  "f010446": "error, Netherlands",
  "f010507": "error, China, Hangzhou",
  "f010513": "error, China, Chongqing",
  "f010558": "error, China, Shenzhen + Hong Kong",
  "f015734": "error, China, Qingdao",
  "f018782": "error, Singapore + Germany, Frankfurt + USA",
  "f019243": "error, USA, Jackson",
  "f020436": "error, China, Beijing",
  "f022395": "error, USA, Los Angeles",
  "f023013": "error, China, Hong Kong",
  "f024468": "error, China, Shenzhen",
  "f024511": "error, NR",
  "f025025": "error, China, Qingdao",
  "f030327": "error, China, Beijing",
  "f034777": "error, China, Chengdu",
  "f039800": "error, China, Chengdu",
  "f042391": "error, China, Fuzhou",
  "f046426": "error, China, Beijing",
  "f047419": "error, USA, Waukesha",
  "f055538": "error, Italy, Genoa",
  "f058369": "error, USA, Bow",
  "f059740": "error, Germany, Korschenbroich",
  "f061059": "error, China, Beijing",
  "f01247": "rejected, undefined",
  "f01272": "rejected, undefined",
  "f02606": "rejected, undefined",
  "f03264": "rejected, undefined",
  "f03340": "rejected, undefined",
  "f03364": "rejected, undefined",
  "f07709": "rejected, undefined",
  "f07819": "rejected, undefined",
  "f08019": "rejected, undefined",
  "f08204": "rejected, undefined",
  "f08403": "rejected, undefined",
  "f010399": "rejected, undefined",
  "f014324": "rejected, undefined",
  "f015233": "rejected, undefined",
  "f016511": "rejected, undefined",
  "f017665": "rejected, undefined",
  "f019041": "rejected, undefined",
  "f019437": "rejected, undefined",
  "f019806": "rejected, undefined",
  "f020385": "rejected, undefined",
  "f020605": "rejected, undefined",
  "f021075": "rejected, undefined",
  "f021532": "rejected, undefined",
  "f021535": "rejected, undefined",
  "f021716": "rejected, undefined",
  "f022227": "rejected, undefined",
  "f022566": "rejected, undefined",
  "f023179": "rejected, undefined",
  "f024146": "rejected, undefined",
  "f024148": "rejected, undefined",
  "f024156": "rejected, undefined",
  "f024550": "rejected, undefined",
  "f030347": "rejected, undefined",
  "f032913": "rejected, undefined",
  "f033189": "rejected, undefined",
  "f033356": "rejected, undefined",
  "f033517": "rejected, undefined",
  "f034039": "rejected, undefined",
  "f034362": "rejected, undefined",
  "f039235": "rejected, undefined",
  "f045714": "rejected, undefined",
  "f048540": "rejected, undefined",
  "f09037": "error-ask, Singapore",
  "f015927": "error-ask, USA, East Islip",
  "f023662": "error-ask, China, Fuzhou",
  "f040218": "error-ask, China, Wuxi",
  "f057618": "error-ask, NR"
}